{
    "exercises": [
        {
            "name": "strings1",
            "path": "exercises/strings/strings1.js",
            "hints": ["Add your hint here"],
            "currentHintIndex": 0,
            "status": "PENDING"
        },
        {
            "name": "numbers1",
            "path": "exercises/numbers/numbers1.js",
            "hints": [
                "How would you add two numbers in real life?",
                "How could you complete the function using a plus sign?"
            ],
            "currentHintIndex": 0,
            "status": "PENDING"
        },
        {
            "name": "numbers2",
            "path": "exercises/numbers/numbers2.js",
            "hints": [
                "JavaScript has built in Math functions. Could you use one to square the number?"
            ],
            "currentHintIndex": 0,
            "status": "PENDING"
        }
    ]
}
